i3pie/__init__.py
i3pie/connection.py
i3pie/consts.py
i3pie/exceptions.py
i3pie/models.py
i3pie/subscriber.py
i3pie-1.0.dist-info/LICENSE.txt
i3pie-1.0.dist-info/METADATA
i3pie-1.0.dist-info/WHEEL
i3pie-1.0.dist-info/top_level.txt
i3pie-1.0.dist-info/RECORD
