Metadata-Version: 2.1
Name: i3pie
Version: 1.0
Summary: IPC library for i3wm
Home-page: https://github.com/gcmt/i3pie
Author: Giacomo Comitti
Author-email: dev@gcomit.com
License: MIT
Keywords: i3 i3wm
Platform: UNKNOWN
Classifier: License :: OSI Approved :: MIT License
Classifier: Programming Language :: Python :: 3.6
Classifier: Programming Language :: Python :: 3.7
Requires-Python: >=3.6
